.gitignore
LICENSE.txt
MANIFEST.in
README.md
__test_dist.bat
__test_install_all.bat
__test_upload_pypi.bat
setup.py
lishixian/__init__.py
lishixian/__main__.py
lishixian/auto.py
lishixian/c.py
lishixian/cls.py
lishixian/dec.py
lishixian/doc.py
lishixian/gui.py
lishixian/line.py
lishixian/new.py
lishixian/np.py
lishixian/reg.py
lishixian/util.py
lishixian/version.py
lishixian/windll.py
lishixian.egg-info/PKG-INFO
lishixian.egg-info/SOURCES.txt
lishixian.egg-info/dependency_links.txt
lishixian.egg-info/entry_points.txt
lishixian.egg-info/top_level.txt
scripts/drag-open.reg
scripts/git-store-pswd.bat
scripts/pip-config.bat
scripts/repair-idle.bat
scripts/restart-explorer.bat
scripts/right-menu.reg
scripts/start-server.bat