Metadata-Version: 2.1
Name: lishixian
Version: 0.4.2
Summary: Lite Software eXtension
Home-page: https://github.com/znsoooo/lishixian
Author: Shixian Li (znsoooo)
Author-email: lsx7@sina.com
License: MIT License
Project-URL: Bug Tracker, https://github.com/znsoooo/lishixian/issues
Keywords: lishixian lsx
Platform: UNKNOWN
Classifier: Programming Language :: Python :: 3
Classifier: Intended Audience :: Developers
Classifier: License :: OSI Approved :: MIT License
